MANIFEST.in
README.rst
setup.py
maxthreads/__init__.py
maxthreads/maxthreads.py
maxthreads/version
maxthreads.egg-info/PKG-INFO
maxthreads.egg-info/SOURCES.txt
maxthreads.egg-info/dependency_links.txt
maxthreads.egg-info/top_level.txt