Metadata-Version: 1.1
Name: maxthreads
Version: 0.4.3
Summary: Python module for queuing threads
Home-page: https://github.com/Zaeb0s/max-threads
Author: Christoffer Zakrisson
Author-email: christoffer_zakrisson@hotmail.com
License: MIT
Keywords: max,threads,thread
Platform: UNKNOWN
Classifier: Development Status :: 3 - Alpha
Classifier: Programming Language :: Python :: 3.5
Classifier: Operating System :: POSIX :: Linux
Classifier: License :: OSI Approved :: MIT License
